MANIFEST.in
README.md
setup.py
example/cal.ics
example/example.ipynb
example/ironman.ics
timetravel/__init__.py
timetravel/parse.py
timetravel/spec.py
timetravel.egg-info/PKG-INFO
timetravel.egg-info/SOURCES.txt
timetravel.egg-info/dependency_links.txt
timetravel.egg-info/top_level.txt