Metadata-Version: 1.1
Name: timetravel
Version: 1.0
Summary: A time machine for your calendar.
Home-page: https://github.com/bmweiner/timetravel
Author: bmweiner
Author-email: bmweiner@users.noreply.github.com
License: MIT License
Platform: py27
Platform: py35
Classifier: Topic :: Software Development :: Libraries :: Python Modules
Classifier: Topic :: Office/Business :: Office Suites
Classifier: Topic :: Office/Business :: Scheduling
Classifier: Topic :: Text Processing :: General
Classifier: Natural Language :: English
Classifier: Operating System :: OS Independent
Classifier: Programming Language :: Python
